collective.contentrules.mailfromfield-1.2.1-py3.11-nspkg.pth
collective/contentrules/mailfromfield/__init__.py
collective/contentrules/mailfromfield/configure.zcml
collective/contentrules/mailfromfield/testing.py
collective/contentrules/mailfromfield/vocabularies.py
collective/contentrules/mailfromfield/actions/__init__.py
collective/contentrules/mailfromfield/actions/configure.zcml
collective/contentrules/mailfromfield/actions/mail.py
collective/contentrules/mailfromfield/locales/collective.contentrules.mailfromfield.pot
collective/contentrules/mailfromfield/locales/plone-manual.pot
collective/contentrules/mailfromfield/locales/plone.pot
collective/contentrules/mailfromfield/locales/rebuildAll.sh
collective/contentrules/mailfromfield/locales/it/LC_MESSAGES/collective.contentrules.mailfromfield.po
collective/contentrules/mailfromfield/locales/it/LC_MESSAGES/plone.po
collective/contentrules/mailfromfield/tests/__init__.py
collective/contentrules/mailfromfield/tests/test_actions_mailfromfield.py
collective.contentrules.mailfromfield-1.2.1.dist-info/METADATA
collective.contentrules.mailfromfield-1.2.1.dist-info/WHEEL
collective.contentrules.mailfromfield-1.2.1.dist-info/entry_points.txt
collective.contentrules.mailfromfield-1.2.1.dist-info/namespace_packages.txt
collective.contentrules.mailfromfield-1.2.1.dist-info/top_level.txt
collective.contentrules.mailfromfield-1.2.1.dist-info/RECORD
