Metadata-Version: 2.1
Name: collective.contentrules.mailfromfield
Version: 1.2.1
Summary: A Plone content rule for send e-mail to addresses taken from the content
Author: RedTurtle Technology
Author-email: sviluppoplone@redturtle.it
License: GPL
Project-URL: PyPI, https://pypi.python.org/pypi/collective.contentrules.mailfromfield
Project-URL: Source, https://github.com/RedTurtle/collective.contentrules.mailfromfield
Project-URL: Tracker, https://github.com/RedTurtle/collective.contentrules.mailfromfield/issues
Keywords: plone rules mail plonegov
Classifier: Framework :: Plone
Classifier: Framework :: Plone :: Addon
Classifier: Framework :: Plone :: 5.2
Classifier: Framework :: Plone :: 6.0
Classifier: Programming Language :: Python
Classifier: Programming Language :: Python :: 2.7
Classifier: Programming Language :: Python :: 3.7
Classifier: Programming Language :: Python :: 3.8
Classifier: Programming Language :: Python :: 3.9
Classifier: Programming Language :: Python :: 3.10
Classifier: Programming Language :: Python :: 3.11
Classifier: Development Status :: 5 - Production/Stable
Classifier: Topic :: Communications :: Email
Classifier: License :: OSI Approved :: GNU General Public License (GPL)
Requires-Python: >=2.7, !=3.0.*, !=3.1.*, !=3.2.*, !=3.3.*, !=3.4.*, !=3.5.*
Requires-Dist: setuptools
Requires-Dist: plone.contentrules
Provides-Extra: test
Requires-Dist: plone.app.robotframework ; extra == 'test'
